pydra_ml/__init__.py
pydra_ml/_version.py
pydra_ml/classifier.py
pydra_ml/cli.py
pydra_ml/report.py
pydra_ml/tasks.py
pydra_ml/tests/__init__.py
pydra_ml/tests/test_classifier.py
pydra_ml/tests/data/breast_cancer.csv
pydra_ml/tests/data/diabetes_table.csv
pydra_ml-0.7.0.dist-info/LICENSE
pydra_ml-0.7.0.dist-info/METADATA
pydra_ml-0.7.0.dist-info/WHEEL
pydra_ml-0.7.0.dist-info/entry_points.txt
pydra_ml-0.7.0.dist-info/top_level.txt
pydra_ml-0.7.0.dist-info/RECORD
